{
  "project_info": {
    "project_number": "894400113551",
    "project_id": "shoppercounter",
    "storage_bucket": "shoppercounter.appspot.com"
  },
  "client": [
    {
      "client_info": {
        "mobilesdk_app_id": "1:894400113551:android:949e7432a530b895c5b9fa",
        "android_client_info": {
          "package_name": "com.shoppercounter"
        }
      },
      "oauth_client": [
        {
          "client_id": "894400113551-1e7k5hv72hjaeasr2f711e8bqepmqcgd.apps.googleusercontent.com",
          "client_type": 3
        }
      ],
      "api_key": [
        {
          "current_key": "AIzaSyBAEKDkCBN3tJ7AaEVvX-NhYBkkzsSB0y8"
        }
      ],
      "services": {
        "appinvite_service": {
          "other_platform_oauth_client": [
            {
              "client_id": "894400113551-1e7k5hv72hjaeasr2f711e8bqepmqcgd.apps.googleusercontent.com",
              "client_type": 3
            }
          ]
        }
      }
    }
  ],
  "configuration_version": "1"
}